MANIFEST.in
README.txt
setup.py
colorsensing/__init__.py
colorsensing/somePython.py
colorsensing.egg-info/PKG-INFO
colorsensing.egg-info/SOURCES.txt
colorsensing.egg-info/dependency_links.txt
colorsensing.egg-info/requires.txt
colorsensing.egg-info/top_level.txt