Metadata-Version: 1.0
Name: colorsensing
Version: 0.1
Summary: An example python package
Home-page: https://github.com/BillMills/python-package-example
Author: Ismael Benito
Author-email: ibenito@color-sensing.com
License: MIT
Platform: UNKNOWN
